sometools/__init__.py
sometools/async_tools/__init__.py
sometools/async_tools/base/__init__.py
sometools/async_tools/base/base.py
sometools/async_tools/bloom_filter/__init__.py
sometools/async_tools/bloom_filter/async_bloomfilter_tool.py
sometools/async_tools/database_tools/__init__.py
sometools/async_tools/database_tools/mysql_tools/__init__.py
sometools/async_tools/database_tools/mysql_tools/async_mysql_orm.py
sometools/async_tools/redis_tools/__init__.py
sometools/async_tools/redis_tools/async_io_redis.py
sometools/sync_tools/__init__.py
sometools/sync_tools/base/__init__.py
sometools/sync_tools/base/base.py
sometools/sync_tools/base64_tools/__init__.py
sometools/sync_tools/base64_tools/base64_tools.py
sometools/sync_tools/calendar_tools/__init__.py
sometools/sync_tools/calendar_tools/calendar_tool.py
sometools/sync_tools/char_tools/__init__.py
sometools/sync_tools/char_tools/char_tools.py
sometools/sync_tools/chinese_to_pinyin_acronym/__init__.py
sometools/sync_tools/chinese_to_pinyin_acronym/chinese_to_pinyin.py
sometools/sync_tools/database_tools/__init__.py
sometools/sync_tools/database_tools/mysql_tools/__init__.py
sometools/sync_tools/database_tools/mysql_tools/conn_pool.py
sometools/sync_tools/datetime_tools/__init__.py
sometools/sync_tools/datetime_tools/date_conversion.py
sometools/sync_tools/encryption_and_decryption_tools/__init__.py
sometools/sync_tools/encryption_and_decryption_tools/aes_tool.py
sometools/sync_tools/encryption_and_decryption_tools/rsa_tool.py
sometools/sync_tools/image_tools/__init__.py
sometools/sync_tools/image_tools/image_tools.py
sometools/sync_tools/ip_tools/__init__.py
sometools/sync_tools/ip_tools/ip_tool.py
sometools/sync_tools/log_tools/__init__.py
sometools/sync_tools/log_tools/logger_main.py
sometools/sync_tools/md5_tools/__init__.py
sometools/sync_tools/md5_tools/md5_tools.py
sometools/sync_tools/multiprocess_tools/__init__.py
sometools/sync_tools/multiprocess_tools/multiprocess_tool.py
SomeTools-0.1.44.dist-info/LICENSE
SomeTools-0.1.44.dist-info/METADATA
SomeTools-0.1.44.dist-info/WHEEL
SomeTools-0.1.44.dist-info/top_level.txt
SomeTools-0.1.44.dist-info/RECORD
